python_mikrotik_login/__init__.py
python_mikrotik_login/md5.py
python_mikrotik_login/mikrotik_login.py
python_mikrotik_login-3.0.8.dist-info/LICENSE
python_mikrotik_login-3.0.8.dist-info/METADATA
python_mikrotik_login-3.0.8.dist-info/WHEEL
python_mikrotik_login-3.0.8.dist-info/top_level.txt
python_mikrotik_login-3.0.8.dist-info/RECORD
