Metadata-Version: 2.1
Name: python-mikrotik-login
Version: 3.0.8
Summary: Python code to login to Mikrotik WebClient without GUI
Home-page: https://github.com/castrix/Python-Mikrotik-WebClient-WiFi-Login
Author: castrix
Author-email: castrix.ihsan@gmail.com
License: UNKNOWN
Platform: UNKNOWN
Classifier: Programming Language :: Python :: 3
Classifier: License :: OSI Approved :: MIT License
Classifier: Operating System :: OS Independent
Requires-Python: >=3.6
Requires-Dist: backports.zoneinfo (==0.2.1)
Requires-Dist: certifi (==2020.12.5)
Requires-Dist: chardet (==4.0.0)
Requires-Dist: idna (==2.10)
Requires-Dist: Js2Py (==0.70)
Requires-Dist: pyjsparser (==2.7.1)
Requires-Dist: requests (==2.25.1)
Requires-Dist: six (==1.15.0)
Requires-Dist: speedtest-cli (==2.1.2)
Requires-Dist: tzlocal (==3.0b1)
Requires-Dist: urllib3 (==1.26.2)
